{"v":"4.8.0","meta":{"g":"LottieFiles AE ","a":"","k":"","d":"","tc":""},"fr":30,"ip":0,"op":150,"w":512,"h":512,"nm":"24. Astronomy","ddd":0,"assets":[{"id":"comp_0","layers":[{"ddd":0,"ind":1,"ty":4,"nm":"Telescope","sr":1,"ks":{"o":{"a":0,"k":100,"ix":11},"r":{"a":0,"k":0,"ix":10},"p":{"a":0,"k":[538.942,568.783,0],"ix":2},"a":{"a":0,"k":[34.375,37.524,0],"ix":1},"s":{"a":0,"k":[600,600,100],"ix":6}},"ao":0,"shapes":[{"ty":"gr","it":[{"ty":"gr","it":[{"ind":0,"ty":"sh","ix":1,"ks":{"a":0,"k":{"i":[[0,0],[0,0],[-0.559,0],[-0.21,0.101],[0.359,0.747],[0,0]],"o":[[0,0],[0.258,0.538],[0.218,0],[0.746,-0.358],[0,0],[0,0]],"v":[[-5.94,-8.999],[2.876,9.369],[4.23,10.221],[4.878,10.072],[5.581,8.071],[-3.199,-10.221]],"c":false},"ix":2},"nm":"Path 1","mn":"ADBE Vector Shape - Group","hd":false},{"ty":"st","c":{"a":0,"k":[0.216000007181,0.277999997606,0.310000011968,1],"ix":3},"o":{"a":0,"k":100,"ix":4},"w":{"a":0,"k":1,"ix":5},"lc":2,"lj":2,"bm":0,"nm":"Stroke 1","mn":"ADBE Vector Graphic - Stroke","hd":false},{"ty":"tr","p":{"a":0,"k":[42.042,55.28],"ix":2},"a":{"a":0,"k":[0,0],"ix":1},"s":{"a":0,"k":[100,100],"ix":3},"r":{"a":0,"k":0,"ix":6},"o":{"a":0,"k":100,"ix":7},"sk":{"a":0,"k":0,"ix":4},"sa":{"a":0,"k":0,"ix":5},"nm":"Transform"}],"nm":"Group 1","np":2,"cix":2,"bm":0,"ix":1,"mn":"ADBE Vector Group","hd":false},{"ty":"gr","it":[{"ind":0,"ty":"sh","ix":1,"ks":{"a":0,"k":{"i":[[0,0],[0,0],[-0.746,-0.358],[-0.359,0.747],[0,0]],"o":[[0,0],[-0.359,0.747],[0.749,0.358],[0,0],[0,0]],"v":[[3.199,-10.326],[-5.581,7.967],[-4.878,9.968],[-2.876,9.265],[5.94,-9.103]],"c":false},"ix":2},"nm":"Path 1","mn":"ADBE Vector Shape - Group","hd":false},{"ty":"st","c":{"a":0,"k":[0.216000007181,0.277999997606,0.310000011968,1],"ix":3},"o":{"a":0,"k":100,"ix":4},"w":{"a":0,"k":1,"ix":5},"lc":2,"lj":2,"bm":0,"nm":"Stroke 1","mn":"ADBE Vector Graphic - Stroke","hd":false},{"ty":"tr","p":{"a":0,"k":[26.5,55.385],"ix":2},"a":{"a":0,"k":[0,0],"ix":1},"s":{"a":0,"k":[100,100],"ix":3},"r":{"a":0,"k":0,"ix":6},"o":{"a":0,"k":100,"ix":7},"sk":{"a":0,"k":0,"ix":4},"sa":{"a":0,"k":0,"ix":5},"nm":"Transform"}],"nm":"Group 2","np":2,"cix":2,"bm":0,"ix":2,"mn":"ADBE Vector Group","hd":false},{"ty":"gr","it":[{"ind":0,"ty":"sh","ix":1,"ks":{"a":0,"k":{"i":[[0,-1.657],[1.657,0],[0,1.657],[-1.657,0]],"o":[[0,1.657],[-1.657,0],[0,-1.657],[1.657,0]],"v":[[3,0],[0,3],[-3,0],[0,-3]],"c":true},"ix":2},"nm":"Path 1","mn":"ADBE Vector Shape - Group","hd":false},{"ty":"st","c":{"a":0,"k":[0.216000007181,0.277999997606,0.310000011968,1],"ix":3},"o":{"a":0,"k":100,"ix":4},"w":{"a":0,"k":1,"ix":5},"lc":2,"lj":2,"bm":0,"nm":"Stroke 1","mn":"ADBE Vector Graphic - Stroke","hd":false},{"ty":"tr","p":{"a":0,"k":[34.271,38.5],"ix":2},"a":{"a":0,"k":[0,0],"ix":1},"s":{"a":0,"k":[100,100],"ix":3},"r":{"a":0,"k":0,"ix":6},"o":{"a":0,"k":100,"ix":7},"sk":{"a":0,"k":0,"ix":4},"sa":{"a":0,"k":0,"ix":5},"nm":"Transform"}],"nm":"Group 4","np":2,"cix":2,"bm":0,"ix":3,"mn":"ADBE Vector Group","hd":false},{"ty":"gr","it":[{"ind":0,"ty":"sh","ix":1,"ks":{"a":0,"k":{"i":[[0,-3.314],[3.313,0],[0,3.313],[-3.313,0]],"o":[[0,3.313],[-3.313,0],[0,-3.314],[3.313,0]],"v":[[6,0],[0,6],[-6,0],[0,-6]],"c":true},"ix":2},"nm":"Path 1","mn":"ADBE Vector Shape - Group","hd":false},{"ty":"st","c":{"a":0,"k":[0.216000007181,0.277999997606,0.310000011968,1],"ix":3},"o":{"a":0,"k":100,"ix":4},"w":{"a":0,"k":1,"ix":5},"lc":2,"lj":2,"bm":0,"nm":"Stroke 1","mn":"ADBE Vector Graphic - Stroke","hd":false},{"ty":"fl","c":{"a":0,"k":[0.936999990426,0.325,0.313999998803,1],"ix":4},"o":{"a":0,"k":100,"ix":5},"r":1,"bm":0,"nm":"Fill 1","mn":"ADBE Vector Graphic - Fill","hd":false},{"ty":"tr","p":{"a":0,"k":[34.271,38.5],"ix":2},"a":{"a":0,"k":[0,0],"ix":1},"s":{"a":0,"k":[100,100],"ix":3},"r":{"a":0,"k":0,"ix":6},"o":{"a":0,"k":100,"ix":7},"sk":{"a":0,"k":0,"ix":4},"sa":{"a":0,"k":0,"ix":5},"nm":"Transform"}],"nm":"Group 10","np":3,"cix":2,"bm":0,"ix":4,"mn":"ADBE Vector Group","hd":false},{"ty":"tr","p":{"a":0,"k":[34.271,49],"ix":2},"a":{"a":0,"k":[34.271,49],"ix":1},"s":{"a":0,"k":[100,100],"ix":3},"r":{"a":0,"k":0,"ix":6},"o":{"a":0,"k":100,"ix":7},"sk":{"a":0,"k":0,"ix":4},"sa":{"a":0,"k":0,"ix":5},"nm":"Transform"}],"nm":"Bottom","np":4,"cix":2,"bm":0,"ix":1,"mn":"ADBE Vector Group","hd":false},{"ty":"gr","it":[{"ty":"gr","it":[{"ind":0,"ty":"sh","ix":1,"ks":{"a":0,"k":{"i":[[0,0],[0,0]],"o":[[0,0],[0,0]],"v":[[-3.061,-7.391],[3.061,7.391]],"c":false},"ix":2},"nm":"Path 1","mn":"ADBE Vector Shape - Group","hd":false},{"ty":"st","c":{"a":0,"k":[0.216000007181,0.277999997606,0.310000011968,1],"ix":3},"o":{"a":0,"k":100,"ix":4},"w":{"a":0,"k":1,"ix":5},"lc":2,"lj":2,"bm":0,"nm":"Stroke 1","mn":"ADBE Vector Graphic - Stroke","hd":false},{"ty":"fl","c":{"a":0,"k":[0.39199999641,0.709999952129,0.964999988032,1],"ix":4},"o":{"a":0,"k":100,"ix":5},"r":1,"bm":0,"nm":"Fill 1","mn":"ADBE Vector Graphic - Fill","hd":false},{"ty":"tr","p":{"a":0,"k":[55.32,21.621],"ix":2},"a":{"a":0,"k":[0,0],"ix":1},"s":{"a":0,"k":[100,100],"ix":3},"r":{"a":0,"k":0,"ix":6},"o":{"a":0,"k":100,"ix":7},"sk":{"a":0,"k":0,"ix":4},"sa":{"a":0,"k":0,"ix":5},"nm":"Transform"}],"nm":"Group 3","np":3,"cix":2,"bm":0,"ix":1,"mn":"ADBE Vector Group","hd":false},{"ty":"gr","it":[{"ind":0,"ty":"sh","ix":1,"ks":{"a":0,"k":{"i":[[0,0],[0,0],[0,0],[0,0],[-0.211,-0.511],[0,0]],"o":[[0,0],[0,0],[0,0],[-0.51,0.211],[0,0],[0,0]],"v":[[-3.886,11.586],[16.372,3.195],[10.249,-11.586],[-15.62,-0.871],[-16.161,0.436],[-13.637,6.529]],"c":false},"ix":2},"nm":"Path 1","mn":"ADBE Vector Shape - Group","hd":false},{"ty":"st","c":{"a":0,"k":[0.216000007181,0.277999997606,0.310000011968,1],"ix":3},"o":{"a":0,"k":100,"ix":4},"w":{"a":0,"k":1,"ix":5},"lc":2,"lj":2,"bm":0,"nm":"Stroke 1","mn":"ADBE Vector Graphic - Stroke","hd":false},{"ty":"tr","p":{"a":0,"k":[45.706,24.286],"ix":2},"a":{"a":0,"k":[0,0],"ix":1},"s":{"a":0,"k":[100,100],"ix":3},"r":{"a":0,"k":0,"ix":6},"o":{"a":0,"k":100,"ix":7},"sk":{"a":0,"k":0,"ix":4},"sa":{"a":0,"k":0,"ix":5},"nm":"Transform"}],"nm":"Group 5","np":2,"cix":2,"bm":0,"ix":2,"mn":"ADBE Vector Group","hd":false},{"ty":"gr","it":[{"ind":0,"ty":"sh","ix":1,"ks":{"a":0,"k":{"i":[[0,0],[-0.765,0],[-1.088,-3.125],[0,0],[0,0],[0,0],[-0.211,-0.511]],"o":[[0.7,-0.2],[3.496,0],[0,0],[0,0],[0,0],[-0.51,0.212],[0,0]],"v":[[-13.637,6.528],[-11.435,6.215],[-3.886,11.587],[16.372,3.196],[10.249,-11.587],[-15.62,-0.871],[-16.161,0.436]],"c":true},"ix":2},"nm":"Path 1","mn":"ADBE Vector Shape - Group","hd":false},{"ty":"fl","c":{"a":0,"k":[1,0.791999966491,0.156999999402,1],"ix":4},"o":{"a":0,"k":100,"ix":5},"r":1,"bm":0,"nm":"Fill 1","mn":"ADBE Vector Graphic - Fill","hd":false},{"ty":"tr","p":{"a":0,"k":[45.706,24.286],"ix":2},"a":{"a":0,"k":[0,0],"ix":1},"s":{"a":0,"k":[100,100],"ix":3},"r":{"a":0,"k":0,"ix":6},"o":{"a":0,"k":100,"ix":7},"sk":{"a":0,"k":0,"ix":4},"sa":{"a":0,"k":0,"ix":5},"nm":"Transform"}],"nm":"Group 6","np":2,"cix":2,"bm":0,"ix":3,"mn":"ADBE Vector Group","hd":false},{"ty":"gr","it":[{"ind":0,"ty":"sh","ix":1,"ks":{"a":0,"k":{"i":[[0,0],[0,0]],"o":[[0,0],[0,0]],"v":[[6.006,-2.488],[-6.006,2.488]],"c":false},"ix":2},"nm":"Path 1","mn":"ADBE Vector Shape - Group","hd":false},{"ty":"st","c":{"a":0,"k":[0.216000007181,0.277999997606,0.310000011968,1],"ix":3},"o":{"a":0,"k":100,"ix":4},"w":{"a":0,"k":1,"ix":5},"lc":2,"lj":2,"bm":0,"nm":"Stroke 1","mn":"ADBE Vector Graphic - Stroke","hd":false},{"ty":"tr","p":{"a":0,"k":[24.113,28.594],"ix":2},"a":{"a":0,"k":[0,0],"ix":1},"s":{"a":0,"k":[100,100],"ix":3},"r":{"a":0,"k":0,"ix":6},"o":{"a":0,"k":100,"ix":7},"sk":{"a":0,"k":0,"ix":4},"sa":{"a":0,"k":0,"ix":5},"nm":"Transform"}],"nm":"Group 7","np":2,"cix":2,"bm":0,"ix":4,"mn":"ADBE Vector Group","hd":false},{"ty":"gr","it":[{"ind":0,"ty":"sh","ix":1,"ks":{"a":0,"k":{"i":[[0,0],[0,0]],"o":[[0,0],[0,0]],"v":[[1.386,-0.574],[-1.386,0.574]],"c":false},"ix":2},"nm":"Path 1","mn":"ADBE Vector Shape - Group","hd":false},{"ty":"st","c":{"a":0,"k":[0.216000007181,0.277999997606,0.310000011968,1],"ix":3},"o":{"a":0,"k":100,"ix":4},"w":{"a":0,"k":1,"ix":5},"lc":2,"lj":2,"bm":0,"nm":"Stroke 1","mn":"ADBE Vector Graphic - Stroke","hd":false},{"ty":"tr","p":{"a":0,"k":[13.951,32.804],"ix":2},"a":{"a":0,"k":[0,0],"ix":1},"s":{"a":0,"k":[100,100],"ix":3},"r":{"a":0,"k":0,"ix":6},"o":{"a":0,"k":100,"ix":7},"sk":{"a":0,"k":0,"ix":4},"sa":{"a":0,"k":0,"ix":5},"nm":"Transform"}],"nm":"Group 8","np":2,"cix":2,"bm":0,"ix":5,"mn":"ADBE Vector Group","hd":false},{"ty":"gr","it":[{"ind":0,"ty":"sh","ix":1,"ks":{"a":0,"k":{"i":[[0,0],[0,0],[0,0],[0,0]],"o":[[0,0],[0,0],[0,0],[0,0]],"v":[[-6.431,-5.847],[-10.126,-4.316],[-5.918,5.847],[10.126,-0.799]],"c":false},"ix":2},"nm":"Path 1","mn":"ADBE Vector Shape - Group","hd":false},{"ty":"st","c":{"a":0,"k":[0.216000007181,0.277999997606,0.310000011968,1],"ix":3},"o":{"a":0,"k":100,"ix":4},"w":{"a":0,"k":1,"ix":5},"lc":2,"lj":2,"bm":0,"nm":"Stroke 1","mn":"ADBE Vector Graphic - Stroke","hd":false},{"ty":"tr","p":{"a":0,"k":[16.225,40.372],"ix":2},"a":{"a":0,"k":[0,0],"ix":1},"s":{"a":0,"k":[100,100],"ix":3},"r":{"a":0,"k":0,"ix":6},"o":{"a":0,"k":100,"ix":7},"sk":{"a":0,"k":0,"ix":4},"sa":{"a":0,"k":0,"ix":5},"nm":"Transform"}],"nm":"Group 9","np":2,"cix":2,"bm":0,"ix":6,"mn":"ADBE Vector Group","hd":false},{"ty":"gr","it":[{"ind":0,"ty":"sh","ix":1,"ks":{"a":0,"k":{"i":[[0,0],[0,0]],"o":[[0,0],[0,0]],"v":[[-1.083,-2.615],[1.083,2.615]],"c":false},"ix":2},"nm":"Path 1","mn":"ADBE Vector Shape - Group","hd":false},{"ty":"st","c":{"a":0,"k":[0.216000007181,0.277999997606,0.310000011968,1],"ix":3},"o":{"a":0,"k":100,"ix":4},"w":{"a":0,"k":1,"ix":5},"lc":2,"lj":2,"bm":0,"nm":"Stroke 1","mn":"ADBE Vector Graphic - Stroke","hd":false},{"ty":"tr","p":{"a":0,"k":[27.506,30.252],"ix":2},"a":{"a":0,"k":[0,0],"ix":1},"s":{"a":0,"k":[100,100],"ix":3},"r":{"a":0,"k":0,"ix":6},"o":{"a":0,"k":100,"ix":7},"sk":{"a":0,"k":0,"ix":4},"sa":{"a":0,"k":0,"ix":5},"nm":"Transform"}],"nm":"Group 11","np":2,"cix":2,"bm":0,"ix":7,"mn":"ADBE Vector Group","hd":false},{"ty":"gr","it":[{"ind":0,"ty":"sh","ix":1,"ks":{"a":0,"k":{"i":[[0.51,-0.211],[0,0],[0.21,0.511],[0,0],[-0.511,0.211],[0,0],[-0.211,-0.51],[0,0]],"o":[[0,0],[-0.511,0.212],[0,0],[-0.211,-0.511],[0,0],[0.51,-0.211],[0,0],[0.211,0.511]],"v":[[2.95,5.814],[2.026,6.196],[0.719,5.655],[-3.49,-4.507],[-2.948,-5.814],[-2.026,-6.197],[-0.719,-5.655],[3.49,4.507]],"c":true},"ix":2},"nm":"Path 1","mn":"ADBE Vector Shape - Group","hd":false},{"ty":"st","c":{"a":0,"k":[0.216000007181,0.277999997606,0.310000011968,1],"ix":3},"o":{"a":0,"k":100,"ix":4},"w":{"a":0,"k":1,"ix":5},"lc":2,"lj":2,"bm":0,"nm":"Stroke 1","mn":"ADBE Vector Graphic - Stroke","hd":false},{"ty":"tr","p":{"a":0,"k":[6.817,41.712],"ix":2},"a":{"a":0,"k":[0,0],"ix":1},"s":{"a":0,"k":[100,100],"ix":3},"r":{"a":0,"k":0,"ix":6},"o":{"a":0,"k":100,"ix":7},"sk":{"a":0,"k":0,"ix":4},"sa":{"a":0,"k":0,"ix":5},"nm":"Transform"}],"nm":"Group 19","np":2,"cix":2,"bm":0,"ix":8,"mn":"ADBE Vector Group","hd":false},{"ty":"gr","it":[{"ind":0,"ty":"sh","ix":1,"ks":{"a":0,"k":{"i":[[0.511,-0.211],[0,0],[0.211,0.51],[0,0],[-0.51,0.212],[0,0],[-0.211,-0.51],[0,0]],"o":[[0,0],[-0.51,0.211],[0,0],[-0.211,-0.51],[0,0],[0.511,-0.212],[0,0],[0.211,0.511]],"v":[[4.48,9.509],[3.556,9.893],[2.249,9.352],[-5.022,-8.203],[-4.48,-9.51],[-3.556,-9.891],[-2.249,-9.351],[5.022,8.203]],"c":true},"ix":2},"nm":"Path 1","mn":"ADBE Vector Shape - Group","hd":false},{"ty":"st","c":{"a":0,"k":[0.216000007181,0.277999997606,0.310000011968,1],"ix":3},"o":{"a":0,"k":100,"ix":4},"w":{"a":0,"k":1,"ix":5},"lc":2,"lj":2,"bm":0,"nm":"Stroke 1","mn":"ADBE Vector Graphic - Stroke","hd":false},{"ty":"tr","p":{"a":0,"k":[60.402,19.516],"ix":2},"a":{"a":0,"k":[0,0],"ix":1},"s":{"a":0,"k":[100,100],"ix":3},"r":{"a":0,"k":0,"ix":6},"o":{"a":0,"k":100,"ix":7},"sk":{"a":0,"k":0,"ix":4},"sa":{"a":0,"k":0,"ix":5},"nm":"Transform"}],"nm":"Group 20","np":2,"cix":2,"bm":0,"ix":9,"mn":"ADBE Vector Group","hd":false},{"ty":"tr","p":{"a":0,"k":[34.042,38.1],"ix":2},"a":{"a":0,"k":[34.042,38.1],"ix":1},"s":{"a":0,"k":[100,100],"ix":3},"r":{"a":1,"k":[{"i":{"x":[0.536],"y":[1]},"o":{"x":[0.43],"y":[0]},"t":0,"s":[20]},{"i":{"x":[0.667],"y":[1]},"o":{"x":[0.333],"y":[0]},"t":45,"s":[0]},{"i":{"x":[0.571],"y":[1]},"o":{"x":[0.454],"y":[0]},"t":90,"s":[0]},{"t":135,"s":[20]}],"ix":6},"o":{"a":0,"k":100,"ix":7},"sk":{"a":0,"k":0,"ix":4},"sa":{"a":0,"k":0,"ix":5},"nm":"Transform"}],"nm":"Lens","np":9,"cix":2,"bm":0,"ix":2,"mn":"ADBE Vector Group","hd":false}],"ip":0,"op":150,"st":0,"bm":0},{"ddd":0,"ind":2,"ty":4,"nm":"Stars","sr":1,"ks":{"o":{"a":0,"k":100,"ix":11},"r":{"a":0,"k":0,"ix":10},"p":{"a":0,"k":[545.691,393.137,0],"ix":2},"a":{"a":0,"k":[35.5,8.25,0],"ix":1},"s":{"a":0,"k":[600,600,100],"ix":6}},"ao":0,"shapes":[{"ty":"gr","it":[{"ind":0,"ty":"sh","ix":1,"ks":{"a":0,"k":{"i":[[0,0],[0,0],[-0.211,0.633],[0,0],[0,0],[-0.634,-0.211],[0,0],[0,0],[0.211,-0.633],[0,0],[0,0],[0.634,0.21]],"o":[[0,0],[0.634,-0.211],[0,0],[0,0],[0.211,0.633],[0,0],[0,0],[-0.634,0.21],[0,0],[0,0],[-0.211,-0.633],[0,0]],"v":[[-3,0],[-1.757,-0.415],[-0.415,-1.756],[0,-3],[0.414,-1.756],[1.756,-0.415],[3,0],[1.756,0.415],[0.414,1.756],[0,3],[-0.415,1.756],[-1.757,0.415]],"c":true},"ix":2},"nm":"Path 1","mn":"ADBE Vector Shape - Group","hd":false},{"ty":"st","c":{"a":0,"k":[0.216000007181,0.277999997606,0.310000011968,1],"ix":3},"o":{"a":0,"k":100,"ix":4},"w":{"a":0,"k":1,"ix":5},"lc":2,"lj":2,"bm":0,"nm":"Stroke 1","mn":"ADBE Vector Graphic - Stroke","hd":false},{"ty":"tr","p":{"a":0,"k":[39.5,11],"ix":2},"a":{"a":0,"k":[0,0],"ix":1},"s":{"a":1,"k":[{"i":{"x":[0.667,0.667],"y":[1,1]},"o":{"x":[0.333,0.333],"y":[0,0]},"t":0,"s":[0,0]},{"i":{"x":[0.667,0.667],"y":[1,1]},"o":{"x":[0.333,0.333],"y":[0,0]},"t":15.6,"s":[105,105]},{"i":{"x":[0.667,0.667],"y":[1,1]},"o":{"x":[0.333,0.333],"y":[0,0]},"t":24,"s":[95,95]},{"i":{"x":[0.833,0.833],"y":[1,1]},"o":{"x":[0.167,0.167],"y":[0,0]},"t":30,"s":[100,100]},{"i":{"x":[0.667,0.667],"y":[1,1]},"o":{"x":[0.167,0.167],"y":[0,0]},"t":120,"s":[100,100]},{"t":135,"s":[0,0]}],"ix":3},"r":{"a":1,"k":[{"i":{"x":[0.833],"y":[0.833]},"o":{"x":[0.167],"y":[0.167]},"t":0,"s":[0]},{"t":150,"s":[360]}],"ix":6},"o":{"a":0,"k":100,"ix":7},"sk":{"a":0,"k":0,"ix":4},"sa":{"a":0,"k":0,"ix":5},"nm":"Transform"}],"nm":"Star","np":2,"cix":2,"bm":0,"ix":1,"mn":"ADBE Vector Group","hd":false},{"ty":"gr","it":[{"ind":0,"ty":"sh","ix":1,"ks":{"a":0,"k":{"i":[[0,0],[0,0],[-0.211,0.633],[0,0],[0,0],[-0.634,-0.211],[0,0],[0,0],[0.211,-0.633],[0,0],[0,0],[0.634,0.21]],"o":[[0,0],[0.634,-0.211],[0,0],[0,0],[0.211,0.633],[0,0],[0,0],[-0.634,0.21],[0,0],[0,0],[-0.211,-0.633],[0,0]],"v":[[-3,0],[-1.757,-0.415],[-0.415,-1.756],[0,-3],[0.414,-1.756],[1.756,-0.415],[3,0],[1.756,0.415],[0.414,1.756],[0,3],[-0.415,1.756],[-1.757,0.415]],"c":true},"ix":2},"nm":"Path 1","mn":"ADBE Vector Shape - Group","hd":false},{"ty":"st","c":{"a":0,"k":[0.216000007181,0.277999997606,0.310000011968,1],"ix":3},"o":{"a":0,"k":100,"ix":4},"w":{"a":0,"k":1,"ix":5},"lc":2,"lj":2,"bm":0,"nm":"Stroke 1","mn":"ADBE Vector Graphic - Stroke","hd":false},{"ty":"tr","p":{"a":1,"k":[{"i":{"x":0.667,"y":1},"o":{"x":0.333,"y":0},"t":0,"s":[31.5,5.5],"to":[0,-0.375],"ti":[0,0]},{"i":{"x":0.667,"y":1},"o":{"x":0.333,"y":0},"t":38,"s":[31.5,3.25],"to":[0,0],"ti":[0,0]},{"i":{"x":0.667,"y":1},"o":{"x":0.333,"y":0},"t":75,"s":[31.5,5.5],"to":[0,0],"ti":[0,0]},{"i":{"x":0.667,"y":1},"o":{"x":0.333,"y":0},"t":113,"s":[31.5,3.25],"to":[0,0],"ti":[0,-0.375]},{"t":150,"s":[31.5,5.5]}],"ix":2},"a":{"a":0,"k":[0,0],"ix":1},"s":{"a":1,"k":[{"i":{"x":[0.667,0.667],"y":[1,1]},"o":{"x":[0.333,0.333],"y":[0,0]},"t":0,"s":[0,0]},{"i":{"x":[0.667,0.667],"y":[1,1]},"o":{"x":[0.333,0.333],"y":[0,0]},"t":15.6,"s":[105,105]},{"i":{"x":[0.667,0.667],"y":[1,1]},"o":{"x":[0.333,0.333],"y":[0,0]},"t":24,"s":[95,95]},{"i":{"x":[0.833,0.833],"y":[1,1]},"o":{"x":[0.167,0.167],"y":[0,0]},"t":30,"s":[100,100]},{"i":{"x":[0.667,0.667],"y":[1,1]},"o":{"x":[0.167,0.167],"y":[0,0]},"t":120,"s":[100,100]},{"t":135,"s":[0,0]}],"ix":3},"r":{"a":1,"k":[{"i":{"x":[0.833],"y":[0.833]},"o":{"x":[0.167],"y":[0.167]},"t":0,"s":[0]},{"t":150,"s":[-360]}],"ix":6},"o":{"a":0,"k":100,"ix":7},"sk":{"a":0,"k":0,"ix":4},"sa":{"a":0,"k":0,"ix":5},"nm":"Transform"}],"nm":"Star","np":2,"cix":2,"bm":0,"ix":2,"mn":"ADBE Vector Group","hd":false}],"ip":0,"op":150,"st":0,"bm":0},{"ddd":0,"ind":3,"ty":4,"nm":"line","parent":4,"sr":1,"ks":{"o":{"a":0,"k":100,"ix":11},"r":{"a":0,"k":0,"ix":10},"p":{"a":0,"k":[15.5,16,0],"ix":2},"a":{"a":0,"k":[15.5,16,0],"ix":1},"s":{"a":0,"k":[100,100,100],"ix":6}},"ao":0,"shapes":[{"ty":"gr","it":[{"ty":"gr","it":[{"ind":0,"ty":"sh","ix":1,"ks":{"a":0,"k":{"i":[[0,0],[0,-0.753],[-7.18,0],[0,1.657],[1.986,0.527]],"o":[[-1.985,0.527],[0,1.657],[7.179,0],[0,-0.753],[0,0]],"v":[[-9.805,-2.483],[-13,-0.517],[0,2.483],[13,-0.517],[9.803,-2.483]],"c":false},"ix":2},"nm":"Path 1","mn":"ADBE Vector Shape - Group","hd":false},{"ty":"tm","s":{"a":1,"k":[{"i":{"x":[0.667],"y":[1]},"o":{"x":[0.333],"y":[0]},"t":143,"s":[0]},{"t":173,"s":[100]}],"ix":1},"e":{"a":1,"k":[{"i":{"x":[0.667],"y":[1]},"o":{"x":[0.333],"y":[0]},"t":128,"s":[0]},{"t":158,"s":[100]}],"ix":2},"o":{"a":0,"k":0,"ix":3},"m":1,"ix":2,"nm":"Trim Paths 1","mn":"ADBE Vector Filter - Trim","hd":false},{"ty":"st","c":{"a":0,"k":[0.216000007181,0.277999997606,0.310000011968,1],"ix":3},"o":{"a":0,"k":100,"ix":4},"w":{"a":0,"k":1,"ix":5},"lc":2,"lj":2,"bm":0,"nm":"Stroke 1","mn":"ADBE Vector Graphic - Stroke","hd":false},{"ty":"tr","p":{"a":0,"k":[15.5,16.517],"ix":2},"a":{"a":0,"k":[0,0],"ix":1},"s":{"a":0,"k":[100,100],"ix":3},"r":{"a":0,"k":0,"ix":6},"o":{"a":0,"k":100,"ix":7},"sk":{"a":0,"k":0,"ix":4},"sa":{"a":0,"k":0,"ix":5},"nm":"Transform"}],"nm":"line 6","np":3,"cix":2,"bm":0,"ix":1,"mn":"ADBE Vector Group","hd":false},{"ty":"gr","it":[{"ind":0,"ty":"sh","ix":1,"ks":{"a":0,"k":{"i":[[0,0],[0,-0.753],[-7.18,0],[0,1.657],[1.986,0.527]],"o":[[-1.985,0.527],[0,1.657],[7.179,0],[0,-0.753],[0,0]],"v":[[-9.805,-2.483],[-13,-0.517],[0,2.483],[13,-0.517],[9.803,-2.483]],"c":false},"ix":2},"nm":"Path 1","mn":"ADBE Vector Shape - Group","hd":false},{"ty":"tm","s":{"a":1,"k":[{"i":{"x":[0.667],"y":[1]},"o":{"x":[0.333],"y":[0]},"t":113,"s":[0]},{"t":143,"s":[100]}],"ix":1},"e":{"a":1,"k":[{"i":{"x":[0.667],"y":[1]},"o":{"x":[0.333],"y":[0]},"t":98,"s":[0]},{"t":128,"s":[100]}],"ix":2},"o":{"a":0,"k":0,"ix":3},"m":1,"ix":2,"nm":"Trim Paths 1","mn":"ADBE Vector Filter - Trim","hd":false},{"ty":"st","c":{"a":0,"k":[0.216000007181,0.277999997606,0.310000011968,1],"ix":3},"o":{"a":0,"k":100,"ix":4},"w":{"a":0,"k":1,"ix":5},"lc":2,"lj":2,"bm":0,"nm":"Stroke 1","mn":"ADBE Vector Graphic - Stroke","hd":false},{"ty":"tr","p":{"a":0,"k":[15.5,16.517],"ix":2},"a":{"a":0,"k":[0,0],"ix":1},"s":{"a":0,"k":[100,100],"ix":3},"r":{"a":0,"k":0,"ix":6},"o":{"a":0,"k":100,"ix":7},"sk":{"a":0,"k":0,"ix":4},"sa":{"a":0,"k":0,"ix":5},"nm":"Transform"}],"nm":"line 5","np":3,"cix":2,"bm":0,"ix":2,"mn":"ADBE Vector Group","hd":false},{"ty":"gr","it":[{"ind":0,"ty":"sh","ix":1,"ks":{"a":0,"k":{"i":[[0,0],[0,-0.753],[-7.18,0],[0,1.657],[1.986,0.527]],"o":[[-1.985,0.527],[0,1.657],[7.179,0],[0,-0.753],[0,0]],"v":[[-9.805,-2.483],[-13,-0.517],[0,2.483],[13,-0.517],[9.803,-2.483]],"c":false},"ix":2},"nm":"Path 1","mn":"ADBE Vector Shape - Group","hd":false},{"ty":"tm","s":{"a":1,"k":[{"i":{"x":[0.667],"y":[1]},"o":{"x":[0.333],"y":[0]},"t":83,"s":[0]},{"t":113,"s":[100]}],"ix":1},"e":{"a":1,"k":[{"i":{"x":[0.667],"y":[1]},"o":{"x":[0.333],"y":[0]},"t":68,"s":[0]},{"t":98,"s":[100]}],"ix":2},"o":{"a":0,"k":0,"ix":3},"m":1,"ix":2,"nm":"Trim Paths 1","mn":"ADBE Vector Filter - Trim","hd":false},{"ty":"st","c":{"a":0,"k":[0.216000007181,0.277999997606,0.310000011968,1],"ix":3},"o":{"a":0,"k":100,"ix":4},"w":{"a":0,"k":1,"ix":5},"lc":2,"lj":2,"bm":0,"nm":"Stroke 1","mn":"ADBE Vector Graphic - Stroke","hd":false},{"ty":"tr","p":{"a":0,"k":[15.5,16.517],"ix":2},"a":{"a":0,"k":[0,0],"ix":1},"s":{"a":0,"k":[100,100],"ix":3},"r":{"a":0,"k":0,"ix":6},"o":{"a":0,"k":100,"ix":7},"sk":{"a":0,"k":0,"ix":4},"sa":{"a":0,"k":0,"ix":5},"nm":"Transform"}],"nm":"line 4","np":3,"cix":2,"bm":0,"ix":3,"mn":"ADBE Vector Group","hd":false},{"ty":"gr","it":[{"ind":0,"ty":"sh","ix":1,"ks":{"a":0,"k":{"i":[[0,0],[0,-0.753],[-7.18,0],[0,1.657],[1.986,0.527]],"o":[[-1.985,0.527],[0,1.657],[7.179,0],[0,-0.753],[0,0]],"v":[[-9.805,-2.483],[-13,-0.517],[0,2.483],[13,-0.517],[9.803,-2.483]],"c":false},"ix":2},"nm":"Path 1","mn":"ADBE Vector Shape - Group","hd":false},{"ty":"tm","s":{"a":1,"k":[{"i":{"x":[0.667],"y":[1]},"o":{"x":[0.333],"y":[0]},"t":53,"s":[0]},{"t":83,"s":[100]}],"ix":1},"e":{"a":1,"k":[{"i":{"x":[0.667],"y":[1]},"o":{"x":[0.333],"y":[0]},"t":38,"s":[0]},{"t":68,"s":[100]}],"ix":2},"o":{"a":0,"k":0,"ix":3},"m":1,"ix":2,"nm":"Trim Paths 1","mn":"ADBE Vector Filter - Trim","hd":false},{"ty":"st","c":{"a":0,"k":[0.216000007181,0.277999997606,0.310000011968,1],"ix":3},"o":{"a":0,"k":100,"ix":4},"w":{"a":0,"k":1,"ix":5},"lc":2,"lj":2,"bm":0,"nm":"Stroke 1","mn":"ADBE Vector Graphic - Stroke","hd":false},{"ty":"tr","p":{"a":0,"k":[15.5,16.517],"ix":2},"a":{"a":0,"k":[0,0],"ix":1},"s":{"a":0,"k":[100,100],"ix":3},"r":{"a":0,"k":0,"ix":6},"o":{"a":0,"k":100,"ix":7},"sk":{"a":0,"k":0,"ix":4},"sa":{"a":0,"k":0,"ix":5},"nm":"Transform"}],"nm":"line 3","np":3,"cix":2,"bm":0,"ix":4,"mn":"ADBE Vector Group","hd":false},{"ty":"gr","it":[{"ind":0,"ty":"sh","ix":1,"ks":{"a":0,"k":{"i":[[0,0],[0,-0.753],[-7.18,0],[0,1.657],[1.986,0.527]],"o":[[-1.985,0.527],[0,1.657],[7.179,0],[0,-0.753],[0,0]],"v":[[-9.805,-2.483],[-13,-0.517],[0,2.483],[13,-0.517],[9.803,-2.483]],"c":false},"ix":2},"nm":"Path 1","mn":"ADBE Vector Shape - Group","hd":false},{"ty":"tm","s":{"a":1,"k":[{"i":{"x":[0.667],"y":[1]},"o":{"x":[0.333],"y":[0]},"t":23,"s":[0]},{"t":53,"s":[100]}],"ix":1},"e":{"a":1,"k":[{"i":{"x":[0.667],"y":[1]},"o":{"x":[0.333],"y":[0]},"t":8,"s":[0]},{"t":38,"s":[100]}],"ix":2},"o":{"a":0,"k":0,"ix":3},"m":1,"ix":2,"nm":"Trim Paths 1","mn":"ADBE Vector Filter - Trim","hd":false},{"ty":"st","c":{"a":0,"k":[0.216000007181,0.277999997606,0.310000011968,1],"ix":3},"o":{"a":0,"k":100,"ix":4},"w":{"a":0,"k":1,"ix":5},"lc":2,"lj":2,"bm":0,"nm":"Stroke 1","mn":"ADBE Vector Graphic - Stroke","hd":false},{"ty":"tr","p":{"a":0,"k":[15.5,16.517],"ix":2},"a":{"a":0,"k":[0,0],"ix":1},"s":{"a":0,"k":[100,100],"ix":3},"r":{"a":0,"k":0,"ix":6},"o":{"a":0,"k":100,"ix":7},"sk":{"a":0,"k":0,"ix":4},"sa":{"a":0,"k":0,"ix":5},"nm":"Transform"}],"nm":"line 2","np":3,"cix":2,"bm":0,"ix":5,"mn":"ADBE Vector Group","hd":false},{"ty":"gr","it":[{"ind":0,"ty":"sh","ix":1,"ks":{"a":0,"k":{"i":[[0,0],[0,-0.753],[-7.18,0],[0,1.657],[1.986,0.527]],"o":[[-1.985,0.527],[0,1.657],[7.179,0],[0,-0.753],[0,0]],"v":[[-9.805,-2.483],[-13,-0.517],[0,2.483],[13,-0.517],[9.803,-2.483]],"c":false},"ix":2},"nm":"Path 1","mn":"ADBE Vector Shape - Group","hd":false},{"ty":"tm","s":{"a":1,"k":[{"i":{"x":[0.667],"y":[1]},"o":{"x":[0.333],"y":[0]},"t":-7,"s":[0]},{"t":23,"s":[100]}],"ix":1},"e":{"a":1,"k":[{"i":{"x":[0.667],"y":[1]},"o":{"x":[0.333],"y":[0]},"t":-22,"s":[0]},{"t":8,"s":[100]}],"ix":2},"o":{"a":0,"k":0,"ix":3},"m":1,"ix":2,"nm":"Trim Paths 1","mn":"ADBE Vector Filter - Trim","hd":false},{"ty":"st","c":{"a":0,"k":[0.216000007181,0.277999997606,0.310000011968,1],"ix":3},"o":{"a":0,"k":100,"ix":4},"w":{"a":0,"k":1,"ix":5},"lc":2,"lj":2,"bm":0,"nm":"Stroke 1","mn":"ADBE Vector Graphic - Stroke","hd":false},{"ty":"tr","p":{"a":0,"k":[15.5,16.517],"ix":2},"a":{"a":0,"k":[0,0],"ix":1},"s":{"a":0,"k":[100,100],"ix":3},"r":{"a":0,"k":0,"ix":6},"o":{"a":0,"k":100,"ix":7},"sk":{"a":0,"k":0,"ix":4},"sa":{"a":0,"k":0,"ix":5},"nm":"Transform"}],"nm":"line","np":3,"cix":2,"bm":0,"ix":6,"mn":"ADBE Vector Group","hd":false},{"ty":"tr","p":{"a":0,"k":[15.5,16],"ix":2},"a":{"a":0,"k":[15.5,16],"ix":1},"s":{"a":0,"k":[100,100],"ix":3},"r":{"a":0,"k":0,"ix":6},"o":{"a":0,"k":100,"ix":7},"sk":{"a":0,"k":0,"ix":4},"sa":{"a":0,"k":0,"ix":5},"nm":"Transform"}],"nm":"Blue Planet","np":6,"cix":2,"bm":0,"ix":1,"mn":"ADBE Vector Group","hd":false}],"ip":0,"op":150,"st":0,"bm":0},{"ddd":0,"ind":4,"ty":4,"nm":"Planet","sr":1,"ks":{"o":{"a":0,"k":100,"ix":11},"r":{"a":1,"k":[{"i":{"x":[0.667],"y":[1]},"o":{"x":[0.333],"y":[0]},"t":0,"s":[0]},{"i":{"x":[0.667],"y":[1]},"o":{"x":[0.333],"y":[0]},"t":38,"s":[14]},{"i":{"x":[0.667],"y":[1]},"o":{"x":[0.333],"y":[0]},"t":113,"s":[-14]},{"t":150,"s":[0]}],"ix":10},"p":{"a":1,"k":[{"i":{"x":0.667,"y":1},"o":{"x":0.333,"y":0},"t":0,"s":[425.693,416.636,0],"to":[0,3.833,0],"ti":[0,0,0]},{"i":{"x":0.667,"y":1},"o":{"x":0.333,"y":0},"t":37.5,"s":[425.693,439.636,0],"to":[0,0,0],"ti":[0,0,0]},{"i":{"x":0.667,"y":1},"o":{"x":0.333,"y":0},"t":75,"s":[425.693,416.636,0],"to":[0,0,0],"ti":[0,0,0]},{"i":{"x":0.667,"y":1},"o":{"x":0.333,"y":0},"t":112.5,"s":[425.693,439.636,0],"to":[0,0,0],"ti":[0,3.833,0]},{"t":150,"s":[425.693,416.636,0]}],"ix":2},"a":{"a":0,"k":[15.5,16,0],"ix":1},"s":{"a":0,"k":[600,600,100],"ix":6}},"ao":0,"shapes":[{"ty":"gr","it":[{"ty":"gr","it":[{"ind":0,"ty":"sh","ix":1,"ks":{"a":0,"k":{"i":[[0,0],[-2.69,0],[-1.45,2.035]],"o":[[1.45,2.035],[2.688,0],[0,0]],"v":[[-6.513,-1.683],[0.001,1.683],[6.513,-1.683]],"c":false},"ix":2},"nm":"Path 1","mn":"ADBE Vector Shape - Group","hd":false},{"ty":"st","c":{"a":0,"k":[0.216000007181,0.277999997606,0.310000011968,1],"ix":3},"o":{"a":0,"k":100,"ix":4},"w":{"a":0,"k":1,"ix":5},"lc":2,"lj":2,"bm":0,"nm":"Stroke 1","mn":"ADBE Vector Graphic - Stroke","hd":false},{"ty":"tr","p":{"a":0,"k":[15.499,22.317],"ix":2},"a":{"a":0,"k":[0,0],"ix":1},"s":{"a":0,"k":[100,100],"ix":3},"r":{"a":0,"k":0,"ix":6},"o":{"a":0,"k":100,"ix":7},"sk":{"a":0,"k":0,"ix":4},"sa":{"a":0,"k":0,"ix":5},"nm":"Transform"}],"nm":"Group 14","np":2,"cix":2,"bm":0,"ix":1,"mn":"ADBE Vector Group","hd":false},{"ty":"gr","it":[{"ind":0,"ty":"sh","ix":1,"ks":{"a":0,"k":{"i":[[0,0],[0,0.112],[4.418,0],[0,-4.418],[-0.005,-0.11]],"o":[[0.005,-0.111],[0,-4.418],[-4.419,0],[0,0.112],[0,0]],"v":[[7.982,4.166],[8,3.834],[0,-4.166],[-8,3.834],[-7.984,4.166]],"c":false},"ix":2},"nm":"Path 1","mn":"ADBE Vector Shape - Group","hd":false},{"ty":"st","c":{"a":0,"k":[0.216000007181,0.277999997606,0.310000011968,1],"ix":3},"o":{"a":0,"k":100,"ix":4},"w":{"a":0,"k":1,"ix":5},"lc":2,"lj":2,"bm":0,"nm":"Stroke 1","mn":"ADBE Vector Graphic - Stroke","hd":false},{"ty":"tr","p":{"a":0,"k":[15.5,12.166],"ix":2},"a":{"a":0,"k":[0,0],"ix":1},"s":{"a":0,"k":[100,100],"ix":3},"r":{"a":0,"k":0,"ix":6},"o":{"a":0,"k":100,"ix":7},"sk":{"a":0,"k":0,"ix":4},"sa":{"a":0,"k":0,"ix":5},"nm":"Transform"}],"nm":"Group 15","np":2,"cix":2,"bm":0,"ix":2,"mn":"ADBE Vector Group","hd":false},{"ty":"gr","it":[{"ind":0,"ty":"sh","ix":1,"ks":{"a":0,"k":{"i":[[1.643,0],[2.434,0.3],[-2.689,0],[-1.451,2.034]],"o":[[-1.644,0],[1.451,2.034],[2.688,0],[-2.434,0.3]],"v":[[0.001,-1.317],[-6.513,-1.683],[0.001,1.683],[6.513,-1.683]],"c":true},"ix":2},"nm":"Path 1","mn":"ADBE Vector Shape - Group","hd":false},{"ty":"fl","c":{"a":0,"k":[0.39199999641,0.709999952129,0.964999988032,1],"ix":4},"o":{"a":0,"k":100,"ix":5},"r":1,"bm":0,"nm":"Fill 1","mn":"ADBE Vector Graphic - Fill","hd":false},{"ty":"tr","p":{"a":0,"k":[15.499,22.317],"ix":2},"a":{"a":0,"k":[0,0],"ix":1},"s":{"a":0,"k":[100,100],"ix":3},"r":{"a":0,"k":0,"ix":6},"o":{"a":0,"k":100,"ix":7},"sk":{"a":0,"k":0,"ix":4},"sa":{"a":0,"k":0,"ix":5},"nm":"Transform"}],"nm":"blue","np":2,"cix":2,"bm":0,"ix":3,"mn":"ADBE Vector Group","hd":false},{"ty":"gr","it":[{"ind":0,"ty":"sh","ix":1,"ks":{"a":0,"k":{"i":[[-0.005,-0.111],[-3.387,0],[-1.912,0.371],[0,0.113],[4.418,0],[0,-4.418]],"o":[[1.912,0.371],[3.388,0],[0.005,-0.111],[0,-4.418],[-4.419,0],[0,0.113]],"v":[[-7.983,3.833],[0,4.5],[7.983,3.833],[8,3.5],[0,-4.5],[-8,3.5]],"c":true},"ix":2},"nm":"Path 1","mn":"ADBE Vector Shape - Group","hd":false},{"ty":"fl","c":{"a":0,"k":[0.39199999641,0.709999952129,0.964999988032,1],"ix":4},"o":{"a":0,"k":100,"ix":5},"r":1,"bm":0,"nm":"Fill 1","mn":"ADBE Vector Graphic - Fill","hd":false},{"ty":"tr","p":{"a":0,"k":[15.499,12.5],"ix":2},"a":{"a":0,"k":[0,0],"ix":1},"s":{"a":0,"k":[100,100],"ix":3},"r":{"a":0,"k":0,"ix":6},"o":{"a":0,"k":100,"ix":7},"sk":{"a":0,"k":0,"ix":4},"sa":{"a":0,"k":0,"ix":5},"nm":"Transform"}],"nm":"blue","np":2,"cix":2,"bm":0,"ix":4,"mn":"ADBE Vector Group","hd":false},{"ty":"tr","p":{"a":0,"k":[15.5,16],"ix":2},"a":{"a":0,"k":[15.5,16],"ix":1},"s":{"a":0,"k":[100,100],"ix":3},"r":{"a":0,"k":0,"ix":6},"o":{"a":0,"k":100,"ix":7},"sk":{"a":0,"k":0,"ix":4},"sa":{"a":0,"k":0,"ix":5},"nm":"Transform"}],"nm":"Blue Planet","np":5,"cix":2,"bm":0,"ix":1,"mn":"ADBE Vector Group","hd":false}],"ip":0,"op":150,"st":0,"bm":0}]}],"layers":[{"ddd":0,"ind":1,"ty":0,"nm":"Astronomy","refId":"comp_0","sr":1,"ks":{"o":{"a":0,"k":100,"ix":11},"r":{"a":0,"k":0,"ix":10},"p":{"a":0,"k":[256,256,0],"ix":2},"a":{"a":0,"k":[540,540,0],"ix":1},"s":{"a":0,"k":[100,100,100],"ix":6}},"ao":0,"w":1080,"h":1080,"ip":0,"op":86,"st":-64,"bm":0},{"ddd":0,"ind":2,"ty":0,"nm":"Astronomy","refId":"comp_0","sr":1,"ks":{"o":{"a":0,"k":100,"ix":11},"r":{"a":0,"k":0,"ix":10},"p":{"a":0,"k":[256,256,0],"ix":2},"a":{"a":0,"k":[540,540,0],"ix":1},"s":{"a":0,"k":[100,100,100],"ix":6}},"ao":0,"w":1080,"h":1080,"ip":86,"op":150,"st":86,"bm":0}],"markers":[]}